{
  "condition": "minecraft:entity_properties",
  "entity": "this",
  "predicate": {
    "equipment": {
      "mainhand": {
        "items": [
          "minecraft:acacia_wood",
          "minecraft:activator_rail",
          "minecraft:allay_spawn_egg",
          "minecraft:allium",
          "minecraft:amethyst_block",
          "minecraft:amethyst_cluster",
          "minecraft:amethyst_shard",
          "minecraft:ancient_debris",
          "minecraft:andesite",
          "minecraft:andesite_slab",
          "minecraft:andesite_stairs",
          "minecraft:andesite_wall",
          "minecraft:anvil",
          "minecraft:apple"
        ]
      }
    }
  }
}