{
  "condition": "minecraft:entity_properties",
  "entity": "this",
  "predicate": {
    "equipment": {
      "mainhand": {
        "items": [
          "minecraft:snow_block",
          "minecraft:snowball",
          "minecraft:soul_campfire",
          "minecraft:soul_lantern",
          "minecraft:soul_sand",
          "minecraft:soul_soil",
          "minecraft:soul_torch",
          "minecraft:spawner",
          "minecraft:spectral_arrow",
          "minecraft:spider_eye",
          "minecraft:spider_spawn_egg",
          "minecraft:splash_potion",
          "minecraft:sponge",
          "minecraft:spore_blossom"
        ]
      }
    }
  }
}